{
  "name": "John Stockton",
  "extraction_date": "2025-07-28T09:34:04.787Z",
  "data_source": "Wikipedia infobox - TRUE extraction",
  "raw_infobox": {
    "name": "John Stockton",
    "image": "John Stockton 2022.jpg",
    "caption": "Stockton in 2022",
    "birth_date": "1962",
    "birth_place": "Spokane, Washington, U.S.",
    "height_ft": "6",
    "height_in": "1",
    "weight_lb": "175",
    "high_school": "Gonzaga Preparatory School(Spokane, Washington)",
    "college": "Gonzaga Bulldogs men's basketball (1980–1984)",
    "draft_year": "1984",
    "draft_round": "1",
    "draft_pick": "16",
    "draft_team": "Utah Jazz",
    "career_start": "1984",
    "career_end": "2003",
    "career_position": "Point guard",
    "career_number": "12",
    "years1": "1984–2002",
    "team1": "Utah Jazz",
    "cyears1": "2015–16 NCAA Division I women's basketball season",
    "cteam1": "Montana State Bobcats women's basketball (assistant)",
    "highlights": "* 10× NBA All-Star (1989–1997, 2000)\n* NBA All-Star Game Most Valuable Player Award{{efn|along with Karl Malone}} (1993)\n* 2× All-NBA First Team (1993, 1994)\n* 6× All-NBA Second Team (1987–1989, 1991, 1992, 1995)\n* 3x All-NBA Third Team (1990, 1996, 1998)\n* 5× NBA All-Defensive Second Team (1988, 1990, 1991, 1994, 1996)\n* 9× List of National Basketball Association annual assists leaders (1987–1995)\n* 2× List of National Basketball Association annual steals leaders (1988, 1991)\n* NBA anniversary team (50 Greatest Players in NBA History, NBA 75th Anniversary Team)\n* No. 12 Utah Jazz#Retired numbers\n* West Coast Conference Men's Basketball Player of the Year (1984)\n* 2× First-team All-West Coast Conference (1983, 1984)\n* No. 12 Gonzaga Bulldogs men's basketball#Retired numbers",
    "stats_league": "NBA",
    "stat1label": "Point (basketball)",
    "stat1value": "19,711 (13.1 ppg)",
    "stat2label": "Assist (basketball)",
    "stat2value": "15,806 (10.5 apg)",
    "stat3label": "Steal (basketball)",
    "stat3value": "3,265 (2.2 spg)",
    "hof_player": "john-stockton",
    "cbbaskhof_year": "2017",
    "medal_templates": "{{MedalSport|Men's basketball}}\n{{MedalCountry|the {{USA}}}}\n{{MedalCompetition | Basketball at the Summer Olympics}}\n1992\n1996\n{{Medal|Competition|FIBA AmeriCup}}\n1992\n}}"
  },
  "wikipedia_url": "https://en.wikipedia.org/wiki/John_Stockton",
  "verified": true,
  "personal_info": {
    "full_name": "John Stockton",
    "birth_date": "1962",
    "birth_place": "Spokane, Washington, U.S.",
    "nationality": "",
    "height": "6 ft 1 in (1.85 m)",
    "weight": "175 lb (79 kg)",
    "position": "",
    "high_school": "Gonzaga Preparatory School(Spokane, Washington)"
  },
  "career_info": {
    "draft_year": "1984",
    "draft_round": "1",
    "draft_pick": "16",
    "draft_team": "Utah Jazz",
    "career_start": "1984",
    "career_end": "2003",
    "current_team": ""
  },
  "career_history": [],
  "awards": [],
  "career_stats": {
    "points": 1971113,
    "rebounds": 1580610,
    "assists": 32652,
    "ppg": 0,
    "rpg": 0,
    "apg": 0
  },
  "image_url": "https://upload.wikimedia.org/wikipedia/commons/c/cf/John_Stockton_2022.jpg"
}